Workbook

Sheet Overview
C3: Data Input Spreadsheet Overview
C5: Purpose: This data input spreadsheet collects all the case study specific data that is
C6: fed into the optimization model. An advanced algorithm then considers this data along
C7: with any/all constraints specified to determine the best possible solution(s). Those
C8: solutions are then returned to the user as specific recommendations for action (e.g.
C9: haul 2,340 bbl of produced water from production pad A to completions pad B on
C10: Tuesday, March 23). See Figure 1 for a process illustration.
C12: Note 1: None of this data is stored in the model permanently. The model and the data
C13: are intentionally kept separated within the optimization framework.
C15: Note 2: Data is assumed to be deterministic initially. Eventually, users will be able
C16: to specify which inputs are uncertain, and the framework will aim to determine
C17: "robustified" recommendations that are near-optimal across a range of uncertainty
C18: realizations (i.e., "stochastic optimization").
C21: Data Input Tabs | F21: Description
C23: Production Pads | F23: List of all production pads to be considered
C24: Completion Pads | F24: List of all completion pads to be considered
C25: SWD Sites | F25: List of all disposal sites to be considered
C26: Drive Times | F26: Estimated drive times between locations
C27: Completions Demand | F27: Forecasted water demand at completions sites
C28: Flowback Rates | F28: Forecasted flowback rates (post-completions)
C29: Production Rates | F29: Forecated production rates (post-flowback)
C30: Disposal Capacity | F30: Forecasted disposal capacity
C31: Freshwater Costs | F31: Cost for sourcing freshwater for frac
C32: Reuse Costs | F32: Cost for FR/chemicals to reuse produced water
C33: Disposal Costs | F33: Cost for disposing produced water
... C36: Pipeline Expansion | F36: Cost for installing new transfer lines

Sheet Schematic

Sheet Units
A1: Units
A2: INDEX | B2: VALUE | D2: Unit Description | E2: Unit Relationships
A3: volume | B3: bbl | D3: Volume units are used to represent water flows (e.g. bbl/day), flow capacities, storage capacity, costs etc. | E3: bbl | F3: = | G3: 42 gallons | I3: kbbl | J3: = | K3: 1000 bbl
A4: distance | B4: mile | D4: Distance units are used for defining lengths of pipelines and pipeline expansion costs | E4: kmeter | F4: = | G4: 1000 m
A5: diameter | B5: inch | D5: This unit applies to diameter of pipelines and pipeline expansion costs
A6: concentration | B6: mg/liter | D6: Concentration unit defines water quality (e.g., TDS concentration) | E6: mg/liter | F6: = | G6: ppm
A7: currency | B7: USD | D7: Currency unit defines costs | E7: kUSD | F7: = | G7: 1000 USD
A8: time | B8: day | D8: Time units refers to input data relative to time (e.g., water flows in bbl/day) | AT8: volume | AU8: distance | AV8: diameter | AW8: concentration | AX8: currency | AY8: time | AZ8: pressure | BA8: decision_period
A9: pressure | B9: psi | D9: Pressure units when using the hydraulics module | E9: psi | F9: = | G9: 6895 Pa | AT9: bbl | AU9: foot | AV9: inch | AW9: mg/liter | AX9: USD | AY9: day | AZ9: pascal | BA9: day
A10: elevation | B10: foot | D10: Elevation of a network node (including all sites) | AT10: kbbl | AU10: mile | AV10: cm | AW10: kg/liter | AX10: kUSD | AY10: week | AZ10: psi | BA10: week
A11: decision period | B11: week | D11: The decision period is the amount of time in a single decision period or discretization (e.g., T01 is 1 week) | E11: fortnight | F11: = | G11: 2 weeks | I11: month | J11: = | K11: 30.44 days | AU11: meter | BA11: fortnight
A12: mass | B12: g | D12: Mass units is used for measuring emissions coefficients (e.g. 10g per treated produced water bbl). | E12: kg | F12: = | G12: 1000g | AU12: kmeter | BB12: month

Sheet ProductionPads
A1: List of all Production Pad Identifiers [-]

Sheet ProductionTanks
A1: List of all Production Tank Identifiers [-]
A2: A01
A3: A02
A4: A03
A5: A04
A6: A05
A7: A06
A8: A07
A9: A08
A10: A09
A11: A10
A12: A11
... A15: A14

Sheet CompletionsPads
A1: List of all Completion Pad Identifiers [-]

Sheet SWDSites
A1: List of all SWD Sites [-]

Sheet ExternalWaterSources
A1: List of all External Water Source Identifiers [-]

Sheet WaterQualityComponents
A1: List of all Water Quality Components [-]
A2: TDS

Sheet AirEmissionsComponents
A1: List of all Air Emissions Components [-]
A2: CO2
A3: NH3
A4: NOx
A5: SO2
A6: PM 2.5

Sheet StorageSites
A1: List of all Storage Site Identifiers [-] | Note: These correspond with Clean Brine Treatment Facilities

Sheet TreatmentSites
A1: List of all Treatment Site Identifiers [-]

Sheet TreatmentTechnologies
A1: List of all Treatment Site Identifiers [-]
A2: CB
A3: CB-EV
A4: MVC
A5: MD
A6: OARO

Sheet ReuseOptions
A1: List of all Reuse Option Identifiers [-]

Sheet NetworkNodes
A1: List of all Network Node Identifiers [-]

Sheet PipelineDiameters
A1: List of all Pipeline Diameter Identifiers [-]
A2: D0
A3: D4
A4: D6
A5: D8
A6: D12

Sheet StorageCapacities
A1: List of all Storage Capacity Identifiers [-]
A2: C0
A3: C1
A4: C2
A5: C3

Sheet TreatmentCapacities
A1: List of all Treatment Capacity Identifiers [-]
A2: J0
A3: J1
A4: J2
A5: J3

Sheet InjectionCapacities
A1: List of all Injection Capacity Identifiers [-]
A2: I0
A3: I1
A4: I2
A5: I3

Sheet PNA
A1: Production Pads to Network Nodes Piping Arcs [-]
A2: ProductionPads

Sheet CNA
A1: Completions Pads to Network Nodes Piping Arcs [-]
A2: CompletionsPads

Sheet CCA
A1: Completions Pads to Completions Pads Piping Arcs [-]
A2: CompletionsPads

Sheet NNA
A1: Network Nodes to Network Nodes Piping Arcs [-]
A2: NetworkNodes

Sheet NCA
A1: Network Nodes to Completions Pads Piping Arcs [-]
A2: NetworkNodes

Sheet NKA
A1: Network Nodes to Disposal Sites Piping Arcs [-]
A2: NetworkNodes

Sheet NRA
A1: Network Nodes to Treatment Sites Piping Arcs [-]
A2: NetworkNodes

Sheet NSA
A1: Network Nodes to Storage Sites Piping Arcs [-]
A2: NetworkNodes

Sheet NOA
A1: Network Nodes to Beneficial Reuse Piping Arcs [-]
A2: NetworkNodes

Sheet SNA
A1: Storage Sites to Network Nodes Piping Arcs [-]
A2: StorageSites

Sheet SOA
A1: Storage Sites to Beneficial Reuse Piping Arcs [-]
A2: StorageSites

Sheet FCA
A1: External Water Sources to Completions Pads Piping Arcs [-]
A2: ExternalWaterSources

Sheet RCA
A1: Treatment Sites to Completions Sites Piping Arcs (1 denotes an arc for the treated stream and 2 denotes an arc for the residual stream) [-]
A2: TreatmentSites

Sheet RSA
A1: Treatment Sites to Storage Sites Piping Arcs (1 denotes an arc for the treated stream and 2 denotes an arc for the residual stream) [-]
A2: TreatmentSites

Sheet SCA
A1: Storage Sites to Completions Piping Arcs [-]
A2: StorageSites

Sheet RNA
A1: Treatment Sites to Network Nodes Piping Arcs (1 denotes an arc for the treated stream and 2 denotes an arc for the residual stream) [-]
A2: TreatmentSites

Sheet RKA
A1: Treatment Sites to Disposal Piping Arcs (1 denotes an arc for the treated stream and 2 denotes an arc for the residual stream) [-]
A2: TreatmentSites

Sheet ROA
A1: Treatment Sites to Beneficial Reuse Piping Arcs (1 denotes an arc for the treated stream and 2 denotes an arc for the residual stream) [-]
A2: TreatmentSites

Sheet PCT
A1: Production Pads to Completions Pads Trucking Arcs [-]
A2: ProductionPads

Sheet FCT
A1: External Water Sources to Completions Pads Trucking Arcs [-]
A2: ExternalWaterSources

Sheet PKT
A1: Production Pads to Disposal Sites Trucking Arcs [-]
A2: ProductionPads

Sheet CKT
A1: Completions Pads to Disposal Sites Trucking Arcs [-]
A2: CompletionsPads

Sheet CCT
A1: Completions Pads to Completions Pads Trucking Arcs [-]
A2: CompletionsPads

Sheet CST
A1: Completions Pads to Storage Sites Trucking Arcs [-]
A2: CompletionsPads

Sheet RST
A1: Treatment Sites to Storage Sites Trucking Arcs (1 denotes an arc for the treated stream and 2 denotes an arc for the residual stream) [-]
A2: TreatmentSites

Sheet ROT
A1: Treatment Sites to Beneficial Reuse Trucking Arcs (1 denotes an arc for the treated stream and 2 denotes an arc for the residual stream) [-]
A2: TreatmentSites

Sheet SOT
A1: Storage Sites to Beneficial Reuse Trucking Arcs [-]
A2: StorageSites

Sheet RKT
A1: Treatment Sites to Disposal Trucking Arcs (1 denotes an arc for the treated stream and 2 denotes an arc for the residual stream) [-]
A2: TreatmentSites

Sheet Elevation
A1: Elevation Data in ft
A2: NODES | B2: VALUE

Sheet CompletionsDemand
A1: =_xlfn.CONCAT( "Table of Completions Water Demand for Completions Sites over ",VLOOKUP("decision period", Units!$A$2:$B$11, 2, FALSE),"s [",VLOOKUP("volume", Units!$A$2:$B$11, 2, FALSE),"/", VLOOKUP("time", Units!$A$2:$B$11, 2, FALSE),"]") -> Table of Completions Water Demand for Completions Sites over weeks [bbl/day]
A2: CompletionsPads | B2: T01 | C2: T02 | D2: T03 | E2: T04 | F2: T05 | G2: T06 | H2: T07 | I2: T08 | J2: T09 | K2: T10 | L2: T11 | M2: T12 | N2: T13 | O2: T14 | P2: T15 | Q2: T16 | R2: T17 | S2: T18 | T2: T19 | U2: T20 | V2: T21 | W2: T22 | X2: T23 | Y2: T24 | Z2: T25 | AA2: T26 | AB2: T27 | AC2: T28 | AD2: T29 | AE2: T30 | AF2: T31 | AG2: T32 | AH2: T33 | AI2: T34 | AJ2: T35 | AK2: T36 | AL2: T37 | AM2: T38 | AN2: T39 | AO2: T40 | AP2: T41 | AQ2: T42 | AR2: T43 | AS2: T44 | AT2: T45 | AU2: T46 | AV2: T47 | AW2: T48 | AX2: T49 | AY2: T50 | AZ2: T51 | BA2: T52

Sheet PadRates
A1: =_xlfn.CONCAT( "Table of Production Rate Forecasts by Pads [",VLOOKUP("volume", Units!$A$2:$B$11, 2, FALSE),"/", VLOOKUP("time", Units!$A$2:$B$11, 2, FALSE),"]") -> Table of Production Rate Forecasts by Pads [bbl/day]
A2: ProductionPads | B2: T01 | C2: T02 | D2: T03 | E2: T04 | F2: T05 | G2: T06 | H2: T07 | I2: T08 | J2: T09 | K2: T10 | L2: T11 | M2: T12 | N2: T13 | O2: T14 | P2: T15 | Q2: T16 | R2: T17 | S2: T18 | T2: T19 | U2: T20 | V2: T21 | W2: T22 | X2: T23 | Y2: T24 | Z2: T25 | AA2: T26 | AB2: T27 | AC2: T28 | AD2: T29 | AE2: T30 | AF2: T31 | AG2: T32 | AH2: T33 | AI2: T34 | AJ2: T35 | AK2: T36 | AL2: T37 | AM2: T38 | AN2: T39 | AO2: T40 | AP2: T41 | AQ2: T42 | AR2: T43 | AS2: T44 | AT2: T45 | AU2: T46 | AV2: T47 | AW2: T48 | AX2: T49 | AY2: T50 | AZ2: T51 | BA2: T52

Sheet FlowbackRates
A1: =_xlfn.CONCAT( "Table of Flowback Rate Forecasts by Pads [",VLOOKUP("volume", Units!$A$2:$B$11, 2, FALSE),"/", VLOOKUP("time", Units!$A$2:$B$11, 2, FALSE),"]") -> Table of Flowback Rate Forecasts by Pads [bbl/day]
A2: CompletionsPads | B2: T01 | C2: T02 | D2: T03 | E2: T04 | F2: T05 | G2: T06 | H2: T07 | I2: T08 | J2: T09 | K2: T10 | L2: T11 | M2: T12 | N2: T13 | O2: T14 | P2: T15 | Q2: T16 | R2: T17 | S2: T18 | T2: T19 | U2: T20 | V2: T21 | W2: T22 | X2: T23 | Y2: T24 | Z2: T25 | AA2: T26 | AB2: T27 | AC2: T28 | AD2: T29 | AE2: T30 | AF2: T31 | AG2: T32 | AH2: T33 | AI2: T34 | AJ2: T35 | AK2: T36 | AL2: T37 | AM2: T38 | AN2: T39 | AO2: T40 | AP2: T41 | AQ2: T42 | AR2: T43 | AS2: T44 | AT2: T45 | AU2: T46 | AV2: T47 | AW2: T48 | AX2: T49 | AY2: T50 | AZ2: T51 | BA2: T52

Sheet WellPressure
A1: Table of Production Rate Forecasts by Pads [bbl/day] | E1: Flow-pressure assumption | H1: 150 psi for 15000 bbl/day and 15 psi for 1500 bbl/day | O1: Flow multiplier | Q1: 0.01
A2: NODES | B2: T01 | C2: T02 | D2: T03 | E2: T04 | F2: T05 | G2: T06 | H2: T07 | I2: T08 | J2: T09 | K2: T10 | L2: T11 | M2: T12 | N2: T13 | O2: T14 | P2: T15 | Q2: T16 | R2: T17 | S2: T18 | T2: T19 | U2: T20 | V2: T21 | W2: T22 | X2: T23 | Y2: T24 | Z2: T25 | AA2: T26 | AB2: T27 | AC2: T28 | AD2: T29 | AE2: T30 | AF2: T31 | AG2: T32 | AH2: T33 | AI2: T34 | AJ2: T35 | AK2: T36 | AL2: T37 | AM2: T38 | AN2: T39 | AO2: T40 | AP2: T41 | AQ2: T42 | AR2: T43 | AS2: T44 | AT2: T45 | AU2: T46 | AV2: T47 | AW2: T48 | AX2: T49 | AY2: T50 | AZ2: T51 | BA2: T52

Sheet InitialPipelineCapacity
A1: =_xlfn.CONCAT( "Table of Initial Pipeline Capacity between Sites [",VLOOKUP("volume", Units!$A$2:$B$11, 2, FALSE),"/", VLOOKUP("time", Units!$A$2:$B$11, 2, FALSE),"]") -> Table of Initial Pipeline Capacity between Sites [bbl/day]
A2: NODES

Sheet InitialPipelineDiameters
A1: Table of Initial Pipeline Diameters between Sites [inch]
A2: NODES

Sheet InitialDisposalCapacity
A1: =_xlfn.CONCAT( "Table of Initial Disposal Capacity [",VLOOKUP("volume", Units!$A$2:$B$11, 2, FALSE),"/", VLOOKUP("time", Units!$A$2:$B$11, 2, FALSE),"]") -> Table of Initial Disposal Capacity [bbl/day]
A2: SWDSites | B2: VALUE

Sheet InitialStorageCapacity
A1: =_xlfn.CONCAT( "Table of Initial Storage Capacity [",VLOOKUP("volume", Units!$A$2:$B$11, 2, FALSE),"]") -> Table of Initial Storage Capacity [bbl]
A2: StorageSites | B2: VALUE

Sheet InitialTreatmentCapacity
A1: =_xlfn.CONCAT( "Table of Initial Treatment Capacity [",VLOOKUP("volume", Units!$A$2:$B$11, 2, FALSE),"/", VLOOKUP("time", Units!$A$2:$B$11, 2, FALSE),"]") -> Table of Initial Treatment Capacity [bbl/day]
A2: TreatmentSites

Sheet ReuseMinimum
A1: =_xlfn.CONCAT( "Table of Beneficial Reuse minimum required flow [",VLOOKUP("volume", Units!$A$2:$B$11, 2, FALSE),"/", VLOOKUP("time", Units!$A$2:$B$11, 2, FALSE),"]") -> Table of Beneficial Reuse minimum required flow [bbl/day]
A2: ReuseOptions | B2: T01 | C2: T02 | D2: T03 | E2: T04 | F2: T05 | G2: T06 | H2: T07 | I2: T08 | J2: T09 | K2: T10 | L2: T11 | M2: T12 | N2: T13 | O2: T14 | P2: T15 | Q2: T16 | R2: T17 | S2: T18 | T2: T19 | U2: T20 | V2: T21 | W2: T22 | X2: T23 | Y2: T24 | Z2: T25 | AA2: T26 | AB2: T27 | AC2: T28 | AD2: T29 | AE2: T30 | AF2: T31 | AG2: T32 | AH2: T33 | AI2: T34 | AJ2: T35 | AK2: T36 | AL2: T37 | AM2: T38 | AN2: T39 | AO2: T40 | AP2: T41 | AQ2: T42 | AR2: T43 | AS2: T44 | AT2: T45 | AU2: T46 | AV2: T47 | AW2: T48 | AX2: T49 | AY2: T50 | AZ2: T51 | BA2: T52

Sheet ReuseCapacity
A1: =_xlfn.CONCAT( "Table of Beneficial Reuse Capacity [",VLOOKUP("volume", Units!$A$2:$B$11, 2, FALSE),"/", VLOOKUP("time", Units!$A$2:$B$11, 2, FALSE),"] (leave cells blank to indicate infinite capacity)") -> Table of Beneficial Reuse Capacity [bbl/day] (leave cells blank to indicate infinite capacity)
A2: ReuseOptions | B2: T01 | C2: T02 | D2: T03 | E2: T04 | F2: T05 | G2: T06 | H2: T07 | I2: T08 | J2: T09 | K2: T10 | L2: T11 | M2: T12 | N2: T13 | O2: T14 | P2: T15 | Q2: T16 | R2: T17 | S2: T18 | T2: T19 | U2: T20 | V2: T21 | W2: T22 | X2: T23 | Y2: T24 | Z2: T25 | AA2: T26 | AB2: T27 | AC2: T28 | AD2: T29 | AE2: T30 | AF2: T31 | AG2: T32 | AH2: T33 | AI2: T34 | AJ2: T35 | AK2: T36 | AL2: T37 | AM2: T38 | AN2: T39 | AO2: T40 | AP2: T41 | AQ2: T42 | AR2: T43 | AS2: T44 | AT2: T45 | AU2: T46 | AV2: T47 | AW2: T48 | AX2: T49 | AY2: T50 | AZ2: T51 | BA2: T52

Sheet ExtWaterSourcingAvailability
A1: =_xlfn.CONCAT( "Table of External Water Sourcing Availability [",VLOOKUP("volume", Units!$A$2:$B$11, 2, FALSE),"/", VLOOKUP("time", Units!$A$2:$B$11, 2, FALSE),"]") -> Table of External Water Sourcing Availability [bbl/day] | E1: F01 | F1: 71428.571 | H1: F02 | I1: 42857.143 | K1: Multiplier | L1: 0.7
A2: ExternalWaterSources | B2: T01 | C2: T02 | D2: T03 | E2: T04 | F2: T05 | G2: T06 | H2: T07 | I2: T08 | J2: T09 | K2: T10 | L2: T11 | M2: T12 | N2: T13 | O2: T14 | P2: T15 | Q2: T16 | R2: T17 | S2: T18 | T2: T19 | U2: T20 | V2: T21 | W2: T22 | X2: T23 | Y2: T24 | Z2: T25 | AA2: T26 | AB2: T27 | AC2: T28 | AD2: T29 | AE2: T30 | AF2: T31 | AG2: T32 | AH2: T33 | AI2: T34 | AJ2: T35 | AK2: T36 | AL2: T37 | AM2: T38 | AN2: T39 | AO2: T40 | AP2: T41 | AQ2: T42 | AR2: T43 | AS2: T44 | AT2: T45 | AU2: T46 | AV2: T47 | AW2: T48 | AX2: T49 | AY2: T50 | AZ2: T51 | BA2: T52

Sheet CompletionsPadStorage
A1: =_xlfn.CONCAT( "Table of Completions Pad Storage Capacity [",VLOOKUP("volume", Units!$A$2:$B$11, 2, FALSE),"]") -> Table of Completions Pad Storage Capacity [bbl]
A2: CompletionsPads | B2: VALUE

Sheet PadOffloadingCapacity
A1: =_xlfn.CONCAT( "Table of Pad Offloading Capacity [",VLOOKUP("volume", Units!$A$2:$B$11, 2, FALSE),"/", VLOOKUP("time", Units!$A$2:$B$11, 2, FALSE),"]") -> Table of Pad Offloading Capacity [bbl/day]
A2: CompletionsPads | B2: VALUE

Sheet NodeCapacities
A1: =_xlfn.CONCAT( "Table of Node Capacity Capacity [",VLOOKUP("volume", Units!$A$2:$B$11, 2, FALSE),"/", VLOOKUP("time", Units!$A$2:$B$11, 2, FALSE),"]", " *absence of node or empty cell signifies no max capacity") -> Table of Node Capacity Capacity [bbl/day] *absence of node or empty cell signifies no max capacity
A2: NODES | B2: VALUE

Sheet DisposalOperatingCapacity
A1: =_xlfn.CONCAT( "Operating Capacity of Disposal Site [%]") -> Operating Capacity of Disposal Site [%]
A2: SWDSites | B2: T01 | C2: T02 | D2: T03 | E2: T04 | F2: T05 | G2: T06 | H2: T07 | I2: T08 | J2: T09 | K2: T10 | L2: T11 | M2: T12 | N2: T13 | O2: T14 | P2: T15 | Q2: T16 | R2: T17 | S2: T18 | T2: T19 | U2: T20 | V2: T21 | W2: T22 | X2: T23 | Y2: T24 | Z2: T25 | AA2: T26 | AB2: T27 | AC2: T28 | AD2: T29 | AE2: T30 | AF2: T31 | AG2: T32 | AH2: T33 | AI2: T34 | AJ2: T35 | AK2: T36 | AL2: T37 | AM2: T38 | AN2: T39 | AO2: T40 | AP2: T41 | AQ2: T42 | AR2: T43 | AS2: T44 | AT2: T45 | AU2: T46 | AV2: T47 | AW2: T48 | AX2: T49 | AY2: T50 | AZ2: T51 | BA2: T52

Sheet DisposalOperationalCost
A1: =_xlfn.CONCAT( "Table of Disposal Operational Cost [",VLOOKUP("currency", Units!$A$2:$B$11, 2, FALSE),"/", VLOOKUP("volume", Units!$A$2:$B$11, 2, FALSE),"]") -> Table of Disposal Operational Cost [USD/bbl]
A2: SWDSites | B2: VALUE

Sheet TreatmentOperationalCost
A1: =_xlfn.CONCAT( "Table of Treatment Operational Cost [",VLOOKUP("currency", Units!$A$2:$B$11, 2, FALSE),"/", VLOOKUP("volume", Units!$A$2:$B$11, 2, FALSE),"]") -> Table of Treatment Operational Cost [USD/bbl]
A2: TreatmentSites | B2: TreatmentTechnologies | C2: VALUE

Sheet ReuseOperationalCost
A1: =_xlfn.CONCAT( "Table of Reuse Operational Cost [",VLOOKUP("currency", Units!$A$2:$B$11, 2, FALSE),"/", VLOOKUP("volume", Units!$A$2:$B$11, 2, FALSE),"]") -> Table of Reuse Operational Cost [USD/bbl]
A2: CompletionsPads | B2: VALUE

Sheet PipelineOperationalCost
A1: =_xlfn.CONCAT( "Table of Pipeline Operational Cost between Sites [",VLOOKUP("currency", Units!$A$2:$B$11, 2, FALSE),"/", VLOOKUP("volume", Units!$A$2:$B$11, 2, FALSE),"]") -> Table of Pipeline Operational Cost between Sites [USD/bbl]
A2: NODES

Sheet ExternalSourcingCost
A1: =_xlfn.CONCAT( "Table of External Water Souring Cost [",VLOOKUP("currency", Units!$A$2:$B$11, 2, FALSE),"/", VLOOKUP("volume", Units!$A$2:$B$11, 2, FALSE),"]") -> Table of External Water Souring Cost [USD/bbl]
A2: ExternalWaterSources | B2: VALUE

Sheet TruckingHourlyCost
A1: =_xlfn.CONCAT( "Table of Trucking Hourly Cost [",VLOOKUP("currency", Units!$A$2:$B$11, 2, FALSE),"/", "hour","]") -> Table of Trucking Hourly Cost [USD/hour]
A2: NODES | B2: VALUE

Sheet TruckingTime
A1: Table of Drive Times between Sites [hours]
A2: NODES

Sheet DisposalExpansionCost
A1: =_xlfn.CONCAT( "Table of Disposal Capacity Expansion Cost [",VLOOKUP("currency", Units!$A$2:$B$11, 2, FALSE),"/(", VLOOKUP("volume", Units!$A$2:$B$11, 2, FALSE),"/", VLOOKUP("time", Units!$A$2:$B$11, 2, FALSE),")]") -> Table of Disposal Capacity Expansion Cost [USD/(bbl/day)]
A2: SWDSites

Sheet DisposalCapacityIncrements
A1: =_xlfn.CONCAT( "Table of Disposal Capacity Expansion Increments [",VLOOKUP("volume", Units!$A$2:$B$11, 2, FALSE),"/", VLOOKUP("time", Units!$A$2:$B$11, 2, FALSE),"]") -> Table of Disposal Capacity Expansion Increments [bbl/day]
A2: InjectionCapacities | B2: VALUE

Sheet StorageExpansionCost
A1: =_xlfn.CONCAT( "Table of Storage Capacity Expansion Cost [",VLOOKUP("currency", Units!$A$2:$B$11, 2, FALSE),"/", VLOOKUP("volume", Units!$A$2:$B$11, 2, FALSE),"]") -> Table of Storage Capacity Expansion Cost [USD/bbl]
A2: StorageSites

Sheet StorageCapacityIncrements
A1: =_xlfn.CONCAT( "Table of Storage Capacity Expansion Increments [",VLOOKUP("volume", Units!$A$2:$B$11, 2, FALSE),"]") -> Table of Storage Capacity Expansion Increments [bbl]
A2: StorageCapacities | B2: VALUE

Sheet TreatmentExpansionCost
A1: =_xlfn.CONCAT( "Table of Treatment Capacity Expansion Cost [",VLOOKUP("currency", Units!$A$2:$B$11, 2, FALSE),"/(", VLOOKUP("volume", Units!$A$2:$B$11, 2, FALSE),"/", VLOOKUP("time", Units!$A$2:$B$11, 2, FALSE),")]") -> Table of Treatment Capacity Expansion Cost [USD/(bbl/day)]
A2: TreatmentSites | B2: TreatmentTechnologies

Sheet TreatmentCapacityIncrements
A1: =_xlfn.CONCAT( "Table of Treatment Capacity Expansion Increments [",VLOOKUP("volume", Units!$A$2:$B$11, 2, FALSE),"/", VLOOKUP("time", Units!$A$2:$B$11, 2, FALSE),"]") -> Table of Treatment Capacity Expansion Increments [bbl/day]
A2: TreatmentCapacities

Sheet PipelineCapexDistanceBased
A1: =_xlfn.CONCAT( "Pipeline Expansion Cost [",VLOOKUP("currency", Units!$A$2:$B$11, 2, FALSE),"/(", VLOOKUP("diameter", Units!$A$2:$B$11, 2, FALSE),"-", VLOOKUP("distance", Units!$A$2:$B$11, 2, FALSE),")]") -> Pipeline Expansion Cost [USD/(inch-mile)]
A2: INDEX | B2: value
A3: pipeline_expansion_cost | B3: 300000

Sheet PipelineExpansionDistance
A1: =_xlfn.CONCAT( "Table of Pipeline Expansion Distances [",VLOOKUP("distance", Units!$A$2:$B$11, 2, FALSE),"]") -> Table of Pipeline Expansion Distances [mile]
A2: NODES

Sheet PipelineCapexCapacityBased
A1: =_xlfn.CONCAT( "Table of Pipeline Capacity Expansion Costs [",VLOOKUP("currency", Units!$A$2:$B$11, 2, FALSE),"/(", VLOOKUP("volume", Units!$A$2:$B$11, 2, FALSE),"/", VLOOKUP("time", Units!$A$2:$B$11, 2, FALSE),")]") -> Table of Pipeline Capacity Expansion Costs [USD/(bbl/day)]
A2: NODES | B2: NODES

Sheet PipelineCapacityIncrements
A1: =_xlfn.CONCAT( "Table of Pipeline Capacity Expansion Increments [",VLOOKUP("volume",#REF!, 2, FALSE),"/", VLOOKUP("time",#REF!, 2, FALSE),"]") -> #REF!
A2: PipelineDiameters | B2: VALUE
A3: D0 | B3: 0
A4: D4 | B4: 14285.714
A5: D6 | B5: 35714.286
A6: D8 | B6: 42857.143
A7: D12 | B7: 50000

Sheet PipelineDiameterValues
A1: =_xlfn.CONCAT( "Table of Pipeline Diameters [",VLOOKUP("diameter", Units!$A$2:$B$11, 2, FALSE),"]") -> Table of Pipeline Diameters [inch]
A2: PipelineDiameters | B2: VALUE

Sheet TreatmentEfficiency
A1: Table of Treatment Efficiency [%]
A2: TreatmentSites | B2: TreatmentTechnologies | C2: VALUE

Sheet RemovalEfficiency
A1: Table of Removal Efficiency [%]. Note: The removal efficiency of a component can be estimated based on its concentration or its total load (flow times concentration). The default method for calculating removal efficacy is concentration-based. This configuration option is set prior to running the optimization. Refer to 'Water Treatment' in Model Library documentation.
A2: TreatmentSites | B2: TreatmentTechnologies | C2: TDS

Sheet DesalinationTechnologies
A1: Table with indication if the treatment technology is for desalination
A2: TreatmentTechnologies | B2: VALUE

Sheet DesalinationSites
A1: Table with Indication if the treatment site is for desalination technologies (1) or non-desalination technologies (0)
A2: TreatmentSites | B2: VALUE

Sheet BeneficialReuseCost
A1: Table with processing cost for sending water to beneficial reuse [USD/bbl]
A2: ReuseOptions | B2: VALUE

Sheet BeneficialReuseCredit
A1: =_xlfn.CONCAT( "Table with credit received for sending water to beneficial reuse [",VLOOKUP("currency", Units!$A$2:$B$11, 2, FALSE),"/", VLOOKUP("volume", Units!$A$2:$B$11, 2, FALSE),"]") -> Table with credit received for sending water to beneficial reuse [USD/bbl]
A2: ReuseOptions | B2: VALUE

Sheet CompletionsPadOutsideSystem
A1: Table with indication if the completions pad is outside of the system
A2: CompletionsPads | B2: VALUE

Sheet Hydraulics
A1: Hydraulic Settings
A2: INDEX | B2: value
A3: roughness | B3: 110
A4: max_head_loss | B4: 0.03
A5: min_allowable_pressure | B5: 10 | C5: psi
A6: max_allowable_pressure | B6: 150 | C6: psi

Sheet Economics
A1: Economic Settings
A2: INDEX | B2: value
A3: discount_rate | B3: 0.08
A4: CAPEX_lifetime | B4: 20

Sheet ExternalWaterQuality
A1: =_xlfn.CONCAT( "Table of Water Quality of External Water Sources [",VLOOKUP("concentration", Units!$A$2:$B$11, 2, FALSE),"]") -> Table of Water Quality of External Water Sources [mg/liter]
A2: ExternalWaterSources | B2: TDS

Sheet PadWaterQuality
A1: =_xlfn.CONCAT( "Table of Water Quality of Produced Water and Flowback Water [",VLOOKUP("concentration", Units!$A$2:$B$11, 2, FALSE),"]") -> Table of Water Quality of Produced Water and Flowback Water [mg/liter]
A2: Pads | B2: TDS

Sheet StorageInitialWaterQuality
A1: =_xlfn.CONCAT( "Table of Initial Water Quality at Storage [", VLOOKUP("concentration", Units!A2:B9, 2, FALSE),,"]") -> Table of Initial Water Quality at Storage [mg/liter]
A2: Pads | B2: TDS

Sheet AirEmissionCoefficients
A1: =_xlfn.CONCAT( "Table of Air Emissions Coefficients ") -> Table of Air Emissions Coefficients
A2: INDEX | B2: CO2 | C2: NH3 | D2: NOx | E2: SO2 | F2: PM 2.5
A3: Trucking [g/hour] | B3: 2035000 | C3: 35.75 | D3: 12650 | E3: 770 | F3: 121
A4: Pipeline Operations [g/(bbl*mile)] | B4: 22 | C4: 0.0002 | D4: 0.014 | E4: 0.0071 | F4: 0.00086
A5: Pipeline Installation [g/mile] | B5: 310000000 | C5: 2800 | D5: 190000 | E5: 100000 | F5: 12000
A6: Disposal [g/bbl] | B6: 970 | C6: 0.13 | D6: 9.5 | E6: 2.8 | F6: 0.87
A7: Storage [g/(bbl*week)] | B7: 1000 | C7: 0.012 | D7: 2 | E7: 0.65 | F7: 0.076

Sheet TreatmentEmissionCoefficients
A1: Table of Air Emissions Coefficients for Treatment Technologies [g/bbl]
A2: TreatmentTechnologies | B2: CO2 | C2: NH3 | D2: NOx | E2: SO2 | F2: PM 2.5
A3: CB | B3: 9600 | C3: 1.45 | D3: 12.8 | E3: 13.5 | F3: 1.5
A4: CB-EV | B4: 9600 | C4: 1.45 | D4: 12.8 | E4: 13.5 | F4: 1.5
A5: MVC | B5: 9600 | C5: 1.45 | D5: 12.8 | E5: 13.5 | F5: 1.5
A6: MD | B6: 9600 | C6: 1.45 | D6: 12.8 | E6: 13.5 | F6: 1.5
A7: OARO | B7: 9600 | C7: 1.45 | D7: 12.8 | E7: 13.5 | F7: 1.5

Sheet PadStorageInitialWaterQuality
A1: =_xlfn.CONCAT( "Table of Initial Water Quality at Completions Pad Storage [",VLOOKUP("concentration", Units!$A$2:$B$11, 2, FALSE),"]") -> Table of Initial Water Quality at Completions Pad Storage [mg/liter]
A2: CompletionsPads | B2: TDS

Sheet TreatmentExpansionLeadTime
A1: =_xlfn.CONCAT( "Table of Treatment Expansion Lead Time [",VLOOKUP("decision period", Units!$A$2:$B$11, 2, FALSE),"s]") -> Table of Treatment Expansion Lead Time [weeks]
A2: TreatmentSites | B2: TreatmentTechnologies

Sheet DisposalExpansionLeadTime
A1: =_xlfn.CONCAT( "Table of Disposal Expansion Lead Time [",VLOOKUP("decision period", Units!$A$2:$B$11, 2, FALSE),"s]") -> Table of Disposal Expansion Lead Time [weeks]
A2: SWDSites

Sheet StorageExpansionLeadTime
A1: =_xlfn.CONCAT( "Table of Storage Expansion Lead Time [",VLOOKUP("decision period", Units!$A$2:$B$11, 2, FALSE),"s]") -> Table of Storage Expansion Lead Time [weeks]
A2: StorageSites

Sheet PipelineExpansionLeadTime_Dist
A1: =_xlfn.CONCAT( "Table of Pipeline Expansion Lead Time - Distance Based [",VLOOKUP("decision period", Units!$A$2:$B$11, 2, FALSE),"s/",VLOOKUP("distance", Units!$A$2:$B$11, 2, FALSE),"]") -> Table of Pipeline Expansion Lead Time - Distance Based [weeks/mile]
A2: INDEX | B2: value
A3: pipeline_expansion_lead_time | B3: 0.2

Sheet PipelineExpansionLeadTime_Capac
A1: =_xlfn.CONCAT( "Table of Pipeline Expansion Lead Time - Capacity Based [",VLOOKUP("decision period",#REF!, 2, FALSE),"s]") -> #REF!
A2: NODES | B2: NODES

Sheet SWDDeep
A1: SWDs - shallow (0) or deep (1)
A2: SWDSites | B2: value

Sheet SWDAveragePressure
A1: Average pressure/depth in vicinity of well [psi/ft]
A2: SWDSites | B2: value

Sheet SWDProxPAWell
A1: Table of SWD proximity to P&A'd well [miles]
A2: SWDSites | B2: value

Sheet SWDProxInactiveWell
A1: Table of SWD proximity to inactive/temporarily abandoned formerly producing well (completed prior to 2000) [miles]
A2: SWDSites | B2: value

Sheet SWDProxEQ
A1: Table of SWD proximity to earthquakes >= 3.0 magnitude [miles]
A2: SWDSites | B2: value

Sheet SWDProxFault
A1: Table of SWD proximity to fault [miles]
A2: SWDSites | B2: value

Sheet SWDProxHpOrLpWell
A1: Table of SWD proximity to high pressure or low pressure injection well [miles]
A2: SWDSites | B2: value

Sheet SWDRiskFactors
A1: SWD risk factors
A2: INDEX | B2: value
A3: orphan_well_distance_risk_factor | B3: 1.86
A4: orphan_well_severity_risk_factor | B4: 2
A5: inactive_well_distance_risk_factor | B5: 1.86
A6: inactive_well_severity_risk_factor | B6: 2
A7: EQ_distance_risk_factor | B7: 5.59
A8: EQ_severity_risk_factor | B8: 1
A9: fault_distance_risk_factor | B9: 5.59
A10: fault_severity_risk_factor | B10: 1
A11: HP_LP_distance_risk_factor | B11: 1.86
A12: HP_LP_severity_risk_factor | B12: 2
A13: HP_threshold | B13: 0.7 | C13: psi/ft
A14: LP_threshold | B14: 0.5 | C14: psi/ft
